{"events":[{"event_id":"f95f783c-7ac0-5773-95da-172df8a14f43","event_date":"1996-10-20","event_kind":"race","event_name":"Shoreview Park/Boeing Creek, Shoreline Community College, Seattle","event_status":null,"result_count":0,"citation_count":1,"organizing_club_id":"019b7ac7-86c3-7b2d-b429-959e9ff3a0b1","organizing_club_name":"Sammamish Orienteering Club"}],"aliases":[],"summary":{"event_count":1,"mention_count":0},"venue_id":"5daddbc7-2595-5526-9f79-2786367a9be0","venue_name":"Shoreview Park/Boeing Creek, Shoreline Community College, Seattle","parent_venue_id":null,"venue_part_type":null,"parent_venue_name":null,"venue_description":null}
