{"courses":[],"event_id":"019b81e3-a50e-7e34-b03e-446ff901389e","venue_id":"019b7b43-5d8c-7e71-8a6e-fb7e4dcf19cf","event_date":"2006-12-16","event_kind":"race","event_name":"WIOL #4/O' Series #4","venue_name":"University of Washington","event_notes":"WinSplits","course_count":0,"event_status":null,"result_count":0,"citation_count":1,"event_comments":null,"external_links":[],"volunteer_roles":[],"organizing_club_id":"01912f3e-e3e1-7e8e-b3c6-32387a8b4990","result_source_brief":"Older COC Results Website: https://www.old.cascadeoc.org/Results.html","organizing_club_name":"Cascade Orienteering Club"}
