{"courses":[],"event_id":"81e941a7-5d84-5a76-8b41-e173882288f3","venue_id":null,"event_date":"1983-10-08","event_kind":"meet","event_name":"EOC COC","venue_name":"Unknown venue","event_notes":"Schedule/source type cell: B.","course_count":0,"event_status":null,"result_count":0,"citation_count":1,"event_comments":null,"external_links":[],"volunteer_roles":[],"organizing_club_id":"01912f3e-e3e1-7e8e-b3c6-32387a8b4990","result_source_brief":"The Northwest Orienteer, July/August 1983","organizing_club_name":"Cascade Orienteering Club"}
