{"events":[{"event_id":"d0485136-9c39-5471-a644-441806f0645f","venue_id":"fe655119-e92d-5b0c-ac30-0330ce9e8058","event_date":"1992-04-26","event_kind":"race","event_name":"Durr Road, Ellensburg","venue_name":"Durr Road, Ellensburg","result_rows":[{"metrics":[],"time_text":"01:24:20","competitive":true,"course_name":"Advanced Course","course_rank":8,"status_code":"OK","affiliations":[],"outcome_text":"01:24:20","overall_rank":8,"result_notes":null,"category_name":null,"category_rank":null,"metric_summary":null,"additional_course":false,"affiliation_labels":[]}],"event_status":null,"result_row_count":1},{"event_id":"a138c798-a155-5f72-bc90-4348253e0bbd","venue_id":null,"event_date":"1991-05-11","event_kind":"race","event_name":"Kittitas Valley O' Festival","venue_name":"Unknown venue","result_rows":[{"metrics":[],"time_text":"02:41:47","competitive":true,"course_name":"Red","course_rank":10,"status_code":"OK","affiliations":[],"outcome_text":"02:41:47","overall_rank":10,"result_notes":null,"category_name":null,"category_rank":null,"metric_summary":null,"additional_course":false,"affiliation_labels":[]}],"event_status":null,"result_row_count":1},{"event_id":"9b7308e9-60d1-56c5-bb4c-1b369052a6ab","venue_id":"b8959813-070b-4811-b2ce-0fc82830b0b0","event_date":"1991-02-16","event_kind":"race","event_name":"Seward Park","venue_name":"Seward Park","result_rows":[{"metrics":[],"time_text":"00:19:30","competitive":true,"course_name":"Course 1","course_rank":6,"status_code":"OK","affiliations":[],"outcome_text":"00:19:30","overall_rank":6,"result_notes":null,"category_name":null,"category_rank":null,"metric_summary":null,"additional_course":false,"affiliation_labels":[]}],"event_status":null,"result_row_count":1}],"aliases":[],"summary":{"role_count":0,"event_count":3,"mention_count":0},"mentions":[],"individual_id":"69a78d96-62d3-47c8-85ca-e28940682cf2","individual_name":"Tom McKay","volunteer_roles":[]}
