{"events":[{"event_id":"7b96addb-4755-513c-a473-d3fdf92ef7bb","venue_id":"019b7ad6-e22e-76b0-9111-fe01c6239c39","event_date":"1996-12-21","event_kind":"race","event_name":"Fort Steilacoom Park","venue_name":"Fort Steilacoom Park","result_rows":[{"metrics":[{"metric_key":"wiol_points","metric_numeric":77}],"time_text":"00:46:31","competitive":true,"course_name":"Course 3 - High School","course_rank":17,"status_code":"OK","affiliations":[{"label":"EVRT"}],"outcome_text":"00:46:31","overall_rank":17,"result_notes":"TPE 72","category_name":"Men","category_rank":null,"metric_summary":"Wiol Points 77","additional_course":false,"affiliation_labels":["EVRT"]}],"event_status":null,"result_row_count":1}],"aliases":[],"summary":{"role_count":0,"event_count":1,"mention_count":0},"mentions":[],"individual_id":"98344a11-e43e-4af1-85a2-a7149f61b207","individual_name":"Josh Irwin","volunteer_roles":[]}
